{
    "BQ_TABLE_PART1": {
        "description": "Es una tabla temporal que almacena el resultado la query del archivo consulta_cero.sql.  Se usa para la generacion de la PlanchaSaldosCero\n\nLa estructura es: dataset.nombre_tabla",
        "value": "dwh_cero.planchaSaldosCero_P1"
    },
    "GCP_CONN_ID": {
        "description": "Nombre de la conexi\u00f3n de Airflow de Google Cloud que se usar\u00e1 en la generaci\u00f3n de planchas. ",
        "value": "google_cloud_default"
    },
    "GCP_PROJECT_ID": {
        "description": "Nombre del proyecto de Google Cloud sobre el que se har\u00e1n las transformaciones y consultas de datos.",
        "value": "data-warehouse-412715"
    },
    "PG_CERO_CONN_ID": {
        "description": "Nombre de la conexi\u00f3n de Airflow para conectarse a la base de datos CERO",
        "value": "cero_postgres"
    },
    "generaDatosClave_Variables": {
        "description": "Configuraci\u00f3n de metadatos, mapeo de tablas de BigQuery y banderas de control para el procesamiento de datos clave de empleados y bolsas.",
        "value": {
            "flags": {
                "executeActualizaEmpleadosBucket": "true",
                "executeBolsaSemanal": "true"
            },
            "params": {
                "puestoAsesor": [
                    145,
                    158
                ]
            },
            "project_id": "data-warehouse-412715",
            "tablas": {
                "cat_buckets_empleados_PROCREA": "ds_procrea.cat_buckets_empleados",
                "cat_buckets_empleados_PROCREA_EXTRA": "dwh_procrea_extrajudicial.cat_buckets_empleados",
                "empleado": "ds_procrea.empleado",
                "ifbolsa_semanal": "dwh_cero.ifbolsa_semanal",
                "ifbolsa_semanal_historico": "dwh_cero.ifbolsa_semanal_historico",
                "puestos": "ds_procrea.puestos",
                "sp_upsert_buckets": "ds_procrea.sp_actualizar_buckets_empleados"
            }
        }
    },
    "generaDatosSaldosBucket_Variables": {
        "description": "Configuraci\u00f3n t\u00e9cnica del proyecto y mapeo de tablas de referencia para la extracci\u00f3n de regiones y cat\u00e1logos de buckets.",
        "value": {
            "flags": {},
            "params": {},
            "project_id": "data-warehouse-412715",
            "tablas": {
                "cat_buckets": "ds_procrea.cat_buckets",
                "regiones": "dwh_consolidado.Pr_regiones"
            }
        }
    }
}